pleasereadme/__init__.py
pleasereadme/entrypoint.py
pleasereadme/gather_user_data.py
pleasereadme/generate_readme.py
please_readme-1.0.0.dist-info/LICENSE
please_readme-1.0.0.dist-info/METADATA
please_readme-1.0.0.dist-info/WHEEL
please_readme-1.0.0.dist-info/entry_points.txt
please_readme-1.0.0.dist-info/top_level.txt
please_readme-1.0.0.dist-info/RECORD
