Metadata-Version: 2.1
Name: please-readme
Version: 1.0.0
Summary: A readme generation package
Home-page: https://github.com/mrmaxguns/please-readme
Author: Maxim Rebguns
Author-email: mrmaxguns@gmail.com
License: UNKNOWN
Keywords: readme README md markdown generator creator maker commandline python package
Platform: UNKNOWN
Classifier: Programming Language :: Python :: 3
Classifier: License :: OSI Approved :: MIT License
Classifier: Operating System :: OS Independent
Requires-Python: >=3.6
